agent_tracing/__init__.py
agent_tracing/database.py
agent_tracing/load_env.py
agent_tracing/tool_tracing.py
agent_tracing/utils.py
robonito_agent_tracing_sdk-0.1.3.dist-info/licenses/LICENSE
robonito_agent_tracing_sdk-0.1.3.dist-info/METADATA
robonito_agent_tracing_sdk-0.1.3.dist-info/WHEEL
robonito_agent_tracing_sdk-0.1.3.dist-info/top_level.txt
robonito_agent_tracing_sdk-0.1.3.dist-info/RECORD
