Metadata-Version: 2.4
Name: robonito-agent-tracing-sdk
Version: 0.1.3
Summary: Python package for tracing LLM-based agents
Author: Mohd Huzaifa
Author-email: mohd.huzaifa@sofyrus.com
License: MIT
Classifier: Programming Language :: Python :: 3
Classifier: License :: OSI Approved :: MIT License
Classifier: Operating System :: OS Independent
Requires-Python: >=3.7
License-File: LICENSE
Provides-Extra: dev
Requires-Dist: pytest; extra == "dev"
Dynamic: license-file
